pypeec/__init__.py
pypeec/main.py
pypeec/script.py
pypeec/data/__init__.py
pypeec/data/banner.txt
pypeec/data/documentation.tar.xz
pypeec/data/examples.tar.xz
pypeec/data/icon.png
pypeec/data/schema_geometry.yaml
pypeec/data/schema_geometry_png.yaml
pypeec/data/schema_geometry_shape.yaml
pypeec/data/schema_geometry_stl.yaml
pypeec/data/schema_geometry_voxel.yaml
pypeec/data/schema_list_plotter.yaml
pypeec/data/schema_list_viewer.yaml
pypeec/data/schema_plot_matplotlib.yaml
pypeec/data/schema_plot_pyvista.yaml
pypeec/data/schema_plot_window.yaml
pypeec/data/schema_problem.yaml
pypeec/data/schema_tolerance.yaml
pypeec/data/version.txt
pypeec/lib_check/__init__.py
pypeec/lib_check/check_data_format.py
pypeec/lib_check/check_data_options.py
pypeec/lib_matrix/__init__.py
pypeec/lib_matrix/green_function.py
pypeec/lib_matrix/matrix_condition.py
pypeec/lib_matrix/matrix_factorization.py
pypeec/lib_matrix/matrix_iterative.py
pypeec/lib_matrix/matrix_multiply.py
pypeec/lib_matrix/multiply_dense.py
pypeec/lib_matrix/multiply_fft.py
pypeec/lib_mesher/__init__.py
pypeec/lib_mesher/mesher_png.py
pypeec/lib_mesher/mesher_shape.py
pypeec/lib_mesher/mesher_stl.py
pypeec/lib_mesher/mesher_voxel.py
pypeec/lib_mesher/voxel_conflict.py
pypeec/lib_mesher/voxel_integrity.py
pypeec/lib_mesher/voxel_point.py
pypeec/lib_mesher/voxel_resampling.py
pypeec/lib_mesher/voxel_summary.py
pypeec/lib_plot/__init__.py
pypeec/lib_plot/manage_matplotlib.py
pypeec/lib_plot/manage_plotgui.py
pypeec/lib_plot/manage_pyvista.py
pypeec/lib_plot/parse_plotter.py
pypeec/lib_plot/parse_viewer.py
pypeec/lib_plot/parse_voxel.py
pypeec/lib_solver/__init__.py
pypeec/lib_solver/equation_solver.py
pypeec/lib_solver/equation_system.py
pypeec/lib_solver/extract_convergence.py
pypeec/lib_solver/extract_solution.py
pypeec/lib_solver/problem_geometry.py
pypeec/lib_solver/problem_value.py
pypeec/lib_solver/sweep_joblib.py
pypeec/lib_solver/system_matrix.py
pypeec/lib_solver/system_tensor.py
pypeec-5.7.4.dist-info/licenses/LICENSE.txt
pypeec-5.7.4.dist-info/METADATA
pypeec-5.7.4.dist-info/WHEEL
pypeec-5.7.4.dist-info/entry_points.txt
pypeec-5.7.4.dist-info/top_level.txt
pypeec-5.7.4.dist-info/RECORD
