Metadata-Version: 2.4
Name: pypeec
Version: 5.7.4
Summary: PyPEEC - 3D Quasi-Magnetostatic Solver
Author-email: Thomas Guillod <guillod@otvam.ch>
Maintainer-email: Thomas Guillod <guillod@otvam.ch>
License-Expression: MPL-2.0
Project-URL: Homepage, https://pypeec.otvam.ch
Project-URL: Repository, https://github.com/otvam/pypeec
Project-URL: Releases, https://github.com/otvam/pypeec/releases
Project-URL: Issues, https://github.com/otvam/pypeec/issues
Project-URL: Paper, https://doi.org/10.21105/joss.06644
Keywords: PyPEEC,FFT,PEEC,3D,voxel,conductor,electric,magnetic,field simulation,maxwell equations,frequency domain,power electronics
Classifier: Environment :: Console
Classifier: Natural Language :: English
Classifier: Intended Audience :: Education
Classifier: Intended Audience :: Science/Research
Classifier: Development Status :: 5 - Production/Stable
Classifier: Operating System :: OS Independent
Classifier: Programming Language :: Python :: 3
Classifier: Programming Language :: Unix Shell
Classifier: Topic :: Scientific/Engineering
Classifier: Topic :: Scientific/Engineering :: Physics
Classifier: Topic :: Scientific/Engineering :: Mathematics
Classifier: Topic :: Scientific/Engineering :: Electronic Design Automation (EDA)
Requires-Python: >=3.10
License-File: LICENSE.txt
Requires-Dist: scilogger>=1.2.5
Requires-Dist: scisave>=1.6.0
Requires-Dist: joblib>=1.3.0
Requires-Dist: numpy>=1.24.0
Requires-Dist: scipy>=1.12.0
Requires-Dist: matplotlib>=3.7.0
Requires-Dist: shapely>=2.0.0
Requires-Dist: rasterio>=1.3.0
Requires-Dist: Pillow>=10.0.0
Requires-Dist: vtk>=9.2.0
Requires-Dist: pyvista>=0.45.0
Requires-Dist: pyvistaqt>=0.11.0
Requires-Dist: pyside6>=6.7.0
Requires-Dist: qtpy>=2.4.0
Dynamic: license-file
